setup.py
pyretimetout/__init__.py
pyretimetout/retry.py
pyretimetout.egg-info/PKG-INFO
pyretimetout.egg-info/SOURCES.txt
pyretimetout.egg-info/dependency_links.txt
pyretimetout.egg-info/not-zip-safe
pyretimetout.egg-info/top_level.txt