Metadata-Version: 1.0
Name: pyretimetout
Version: 2.0.0
Summary: A micro library for timeout and retry operations.
Home-page: http://github.com/rfyiamcool
Author: fengyun rui
Author-email: rfyiamcool@163.com
License: MIT
Platform: UNKNOWN
